	<family name="frobozz_net">
		<parents/>
		<environ>
			<family_variable name="local_address" trait="default">
				192.168.0.1
			</family_variable>
			<family_variable name="local_netmask" trait="default">
				255.255.0.0
			</family_variable>
			<family_variable name="local_network" trait="default">
				192.168.0.0
			</family_variable>
			<family_variable name="reversed_local_zone" trait="default">
				10
			</family_variable>
			<family_variable name="main_range" trait="dhcp_server">
				192.168.0.51 192.168.0.253
			</family_variable>
			<family_variable name="local_netmask" trait="global">
				255.255.0.0
			</family_variable>
			<family_variable name="local_network" trait="global">
				192.168.0.0
			</family_variable>
			<family_variable name="local_network_cidr" trait="global">
				192.168.0.0/16
			</family_variable>
			<family_variable name="rev_local_zone" trait="global">
				10
			</family_variable>
			<family_variable name="cidr" trait="localnet">
				192.168.0.0/16
			</family_variable>
			<family_variable name="first_dynhost" trait="localnet">
				192.168.0.51
			</family_variable>
			<family_variable name="last_dynhost" trait="localnet">
				192.168.0.253
			</family_variable>
			<family_variable name="netmask" trait="localnet">
				255.255.0.0
			</family_variable>
			<family_variable name="network" trait="localnet">
				192.168.0.0
			</family_variable>
			<family_variable name="rev_zone" trait="localnet">
				168.192
			</family_variable>
			<family_variable name="reversed_local_address" trait="nameserver">
				1.0.168.192
			</family_variable>
		</environ>
	</family>
